verilog/ALU.v
module  OR(DATA1,DATA2,RESULT);

    input wire [7:0] DATA1,DATA2;
    output [7:0] RESULT;

    assign RESULT = DATA1 | DATA2;


endmodule

module  AND(DATA1,DATA2,RESULT);

    input wire [7:0] DATA1,DATA2;
    output[7:0] RESULT;

    assign RESULT = DATA1 & DATA2;

endmodule


module  ADD(DATA1,DATA2,RESULT);

    input wire [7:0] DATA1,DATA2;
    output reg[7:0] RESULT;
    always @(*) begin
        if(DATA2<0)
            RESULT = DATA1 - DATA2;
        else
            RESULT = DATA1 + DATA2;
    end

endmodule

module  FORWARD(DATA1,DATA2,RESULT);

    input wire [7:0] DATA1,DATA2;
    output[7:0] RESULT;

    assign RESULT = DATA2;

endmodule








module ALU(DATA1,DATA2,SELECT,RESULT);
    //defining inputs
    input wire [7:0] DATA1,DATA2;
    input wire [2:0] SELECT;
    input CLK;

    //defining outputs
    output reg [7:0] RESULT;
    
    wire [7:0] FORWARD_RESULT;
    wire [7:0]  ADD_RESULT;
    wire [7:0]  AND_RESULT;
    wire [7:0]  OR_RESULT;


    FORWARD dut1(DATA1,DATA2,FORWARD_RESULT);
    ADD dut2(DATA1,DATA2,ADD_RESULT);
    AND dut3(DATA1,DATA2,AND_RESULT);
    OR dut4(DATA1,DATA2,OR_RESULT);


    always @(*) begin
        
        case(SELECT)
        3'b000 : #1 RESULT = FORWARD_RESULT;

        3'b001 : #2 RESULT = ADD_RESULT;

        3'b010 : #1 RESULT = AND_RESULT;

        3'b011 : #1 RESULT = OR_RESULT;
        endcase
    end

endmodule

verilog/ALU_TB.V

`include "ALU.v"


module ALU_TB;

    // Inputs
    reg [7:0] DATA1;
    reg [7:0] DATA2;
    reg [2:0] SELECT;

    // Outputs
    wire [7:0] RESULT;

    // Instantiate the ALU module
    ALU ALU_inst (
        .DATA1(DATA1),
        .DATA2(DATA2),
        .SELECT(SELECT),
        .RESULT(RESULT)
    );

    // Test vectors
    initial begin

    $dumpfile("akakshmodaya.vcd");
    $dumpvars(0, ALU_TB);


        // Initialize inputs
        DATA1 = 8'b10101010;
        DATA2 = 8'b01010101;
        SELECT = 3'b000;

        // Apply stimulus
        #10 DATA1 = 8'b11110000;
        #10 DATA2 = 8'b00001111;
        #10 SELECT = 3'b001;
        #10 SELECT = 3'b010;
        #10 SELECT = 3'b011;

        // Add more test cases as needed...

        // Monitor
        $display("Time=%t, DATA1=%h, DATA2=%h, SELECT=%b, RESULT=%h", $time, DATA1, DATA2, SELECT, RESULT);
        
        // End simulation
        #10 $finish;
    end

endmodule

verilog/akakshmodaya.vcd
$date
	Wed Apr 10 10:40:58 2024
$end
$version
	Icarus Verilog
$end
$timescale
	1s
$end
$scope module ALU_TB $end
$var wire 8 ! RESULT [7:0] $end
$var reg 8 " DATA1 [7:0] $end
$var reg 8 # DATA2 [7:0] $end
$var reg 3 $ SELECT [2:0] $end
$scope module ALU_inst $end
$var wire 1 % CLK $end
$var wire 8 & DATA1 [7:0] $end
$var wire 8 ' DATA2 [7:0] $end
$var wire 3 ( SELECT [2:0] $end
$var wire 8 ) OR_RESULT [7:0] $end
$var wire 8 * FORWARD_RESULT [7:0] $end
$var wire 8 + AND_RESULT [7:0] $end
$var wire 8 , ADD_RESULT [7:0] $end
$var reg 8 - RESULT [7:0] $end
$scope module dut1 $end
$var wire 8 . DATA1 [7:0] $end
$var wire 8 / DATA2 [7:0] $end
$var wire 8 0 RESULT [7:0] $end
$upscope $end
$scope module dut2 $end
$var wire 8 1 DATA1 [7:0] $end
$var wire 8 2 DATA2 [7:0] $end
$var reg 8 3 RESULT [7:0] $end
$upscope $end
$scope module dut3 $end
$var wire 8 4 DATA1 [7:0] $end
$var wire 8 5 DATA2 [7:0] $end
$var wire 8 6 RESULT [7:0] $end
$upscope $end
$scope module dut4 $end
$var wire 8 7 DATA1 [7:0] $end
$var wire 8 8 DATA2 [7:0] $end
$var wire 8 9 RESULT [7:0] $end
$upscope $end
$upscope $end
$upscope $end
$enddefinitions $end
$comment Show the parameter values. $end
$dumpall
$end
#0
$dumpvars
b11111111 9
b1010101 8
b10101010 7
b0 6
b1010101 5
b10101010 4
b11111111 3
b1010101 2
b10101010 1
b1010101 0
b1010101 /
b10101010 .
bx -
b11111111 ,
b0 +
b1010101 *
b11111111 )
b0 (
b1010101 '
b10101010 &
z%
b0 $
b1010101 #
b10101010 "
bx !
$end
#1
b1010101 !
b1010101 -
#10
b1000101 ,
b1000101 3
b1010000 +
b1010000 6
b11110101 )
b11110101 9
b11110000 "
b11110000 &
b11110000 .
b11110000 1
b11110000 4
b11110000 7
#20
b11111111 ,
b11111111 3
b0 +
b0 6
b11111111 )
b11111111 9
b1111 *
b1111 0
b1111 #
b1111 '
b1111 /
b1111 2
b1111 5
b1111 8
#21
b1111 !
b1111 -
#30
b1 $
b1 (
#32
b11111111 !
b11111111 -
#40
b10 $
b10 (
#41
b0 !
b0 -
#50
b11 $
b11 (
#51
b11111111 !
b11111111 -
